argparse_custom_types.py
argparse_custom_types-0.2.0.dist-info/LICENSE
argparse_custom_types-0.2.0.dist-info/METADATA
argparse_custom_types-0.2.0.dist-info/WHEEL
argparse_custom_types-0.2.0.dist-info/top_level.txt
argparse_custom_types-0.2.0.dist-info/RECORD
