Metadata-Version: 2.1
Name: argparse-custom-types
Version: 0.2.0
Summary: argparse custom types
Home-page: https://github.com/tech-chad/argparse-custom-types
Author: Chad Larson
Author-email: techchad2@gmail.com
License: MIT
Platform: UNKNOWN
Classifier: Programming Language :: Python :: 3
Classifier: Programming Language :: Python :: 3.6
Classifier: Programming Language :: Python :: 3.7
Requires-Python: >= 3.6.1
